SLinfra/__init__.py
SLinfra/file_logger.py
SLinfra/state_tracker.py
slinfra-0.2.0.dist-info/licenses/LICENSE
slinfra-0.2.0.dist-info/METADATA
slinfra-0.2.0.dist-info/WHEEL
slinfra-0.2.0.dist-info/top_level.txt
slinfra-0.2.0.dist-info/RECORD
