Metadata-Version: 2.4
Name: SLinfra
Version: 0.2.0
Summary: A lightweight Python utility for file-based logging and persistent state tracking.
Author-email: MJBM <mohamnarut@gmail.com>
License: MIT
Project-URL: Homepage, https://github.com/MJBM2510/infra
Project-URL: Source, https://github.com/MJBM2510/infra
Classifier: Development Status :: 3 - Alpha
Classifier: Intended Audience :: Developers
Classifier: License :: OSI Approved :: MIT License
Classifier: Programming Language :: Python :: 3
Classifier: Programming Language :: Python :: 3.8
Classifier: Operating System :: OS Independent
Requires-Python: >=3.8
License-File: LICENSE
Dynamic: license-file
